pproj/__init__.py
pproj/__main__.py
pproj/project.py
pproj/data/Brewfile
pproj-0.2.26.dist-info/LICENSE
pproj-0.2.26.dist-info/METADATA
pproj-0.2.26.dist-info/WHEEL
pproj-0.2.26.dist-info/entry_points.txt
pproj-0.2.26.dist-info/top_level.txt
pproj-0.2.26.dist-info/RECORD
