Metadata-Version: 2.1
Name: pproj
Version: 0.2.26
Summary: A tool for managing python packages
Author-email: José Antonio Puértolas Montañés <63794670+j5pu@users.noreply.github.com>
License: MIT
Project-URL: Homepage, https://github.com/j5pu/pproj
Requires-Python: >=3.11
License-File: LICENSE
Requires-Dist: rich <14,>=13.6.0
Requires-Dist: tomlkit <1,>=0.12.1
Requires-Dist: typer[all] <1,>=0.9
Provides-Extra: all
Requires-Dist: pproj[dev,docs,tests] ; extra == 'all'
Provides-Extra: dev
Requires-Dist: black[d] <24,>=23.9.1 ; extra == 'dev'
Requires-Dist: build <2,>=1.0.3 ; extra == 'dev'
Requires-Dist: icecream <3,>=2.1.3 ; extra == 'dev'
Requires-Dist: ipython <9,>=8.16.0 ; extra == 'dev'
Requires-Dist: ipython-suggestions <2,>=1.0.0 ; extra == 'dev'
Requires-Dist: restmagic <1,>=0.7.2 ; extra == 'dev'
Requires-Dist: mypy <2,>=1.5.1 ; extra == 'dev'
Requires-Dist: pyflyby <2,>=1.8.6 ; extra == 'dev'
Requires-Dist: twine <5,>=4.0.2 ; extra == 'dev'
Provides-Extra: docs
Requires-Dist: docutils ; extra == 'docs'
Requires-Dist: furo <2024,>=2023.9.10 ; extra == 'docs'
Requires-Dist: myst-parser <3,>=2.0.0 ; extra == 'docs'
Requires-Dist: sphinx <8,>=7.2.6 ; extra == 'docs'
Requires-Dist: sphinx-autodoc-typehints ; extra == 'docs'
Requires-Dist: sphinx-autobuild <2022,>=2021.3.14 ; extra == 'docs'
Requires-Dist: sphinx-click <6,>=5.0.1 ; extra == 'docs'
Requires-Dist: sphinxcontrib-napoleon <1,>=0.7 ; extra == 'docs'
Provides-Extra: tests
Requires-Dist: coverage[toml] <7,>=6 ; extra == 'tests'
Requires-Dist: darglint <2,>=1.8.1 ; extra == 'tests'
Requires-Dist: environs <10,>=9.5.0 ; extra == 'tests'
Requires-Dist: pycodestyle <3,>=2.11.0 ; extra == 'tests'
Requires-Dist: pydocstyle <7,>=6.3 ; extra == 'tests'
Requires-Dist: pytest <8,>=7 ; extra == 'tests'
Requires-Dist: pytest-asyncio <1,>=0.21.1 ; extra == 'tests'
Requires-Dist: pytest-clarity <2,>=1.0.1 ; extra == 'tests'
Requires-Dist: pytest-cov <5,>=4 ; extra == 'tests'
Requires-Dist: pytest-doctestplus <1,>=0.13 ; extra == 'tests'
Requires-Dist: pytest-git <2,>=1.7.0 ; extra == 'tests'
Requires-Dist: pytest-git-fixtures <1,>=0.1.7 ; extra == 'tests'
Requires-Dist: pytest-github-actions-annotate-failures <1,>=0.2.0 ; extra == 'tests'
Requires-Dist: pytest-mock <4,>=3 ; extra == 'tests'
Requires-Dist: pytest-xdist <3,>=2 ; extra == 'tests'
Requires-Dist: pytest-remotedata <1,>=0.4.0 ; extra == 'tests'
Requires-Dist: pytest-lazy-fixture ~=0.6.3 ; extra == 'tests'
Requires-Dist: pytest-sugar <1,>=0.9.7 ; extra == 'tests'
Requires-Dist: responses <1,>=0.21.0 ; extra == 'tests'
Requires-Dist: requests-mock <2,>=1.10.0 ; extra == 'tests'
Requires-Dist: ruff <0.1,>=0.0.282 ; extra == 'tests'
Requires-Dist: ruff-lsp <0.1,>=0.0.39 ; extra == 'tests'
Requires-Dist: tox <5,>=4.6.4 ; extra == 'tests'
Requires-Dist: types-pytest-lazy-fixture >=0.6.3.3 ; extra == 'tests'
Requires-Dist: xdoctest <2,>=1.1.1 ; extra == 'tests'
